microSALT/__init__.py
microSALT/cli.py
microSALT/server/__init__.py
microSALT/server/app.py
microSALT/server/views.py
microSALT/server/templates/STtracker_page.html
microSALT/server/templates/alignment_page.html
microSALT/server/templates/bootstrap.html
microSALT/server/templates/layout.html
microSALT/server/templates/project_page.html
microSALT/server/templates/start_page.html
microSALT/server/templates/typing_page.html
microSALT/store/__init__.py
microSALT/store/db_manipulator.py
microSALT/store/models.py
microSALT/store/orm_models.py
microSALT/utils/__init__.py
microSALT/utils/job_creator.py
microSALT/utils/referencer.py
microSALT/utils/reporter.py
microSALT/utils/scraper.py
microSALT-3.0.1.data/data/expec/ExPEC.fsa
microSALT-3.0.1.data/data/logos/microsalt.jpg
microSALT-3.0.1.data/data/logos/swedac.jpg
microSALT-3.0.1.data/data/testdata/alignment.stats.cov
microSALT-3.0.1.data/data/testdata/alignment.stats.dup
microSALT-3.0.1.data/data/testdata/alignment.stats.ins
microSALT-3.0.1.data/data/testdata/alignment.stats.map
microSALT-3.0.1.data/data/testdata/alignment.stats.raw
microSALT-3.0.1.data/data/testdata/alignment.stats.ref
microSALT-3.0.1.data/data/testdata/blast_single_loci.txt
microSALT-3.0.1.data/data/testdata/blast_single_resistance.txt
microSALT-3.0.1.data/data/testdata/configExample.json
microSALT-3.0.1.data/data/testdata/quast_results.tsv
microSALT-3.0.1.data/data/testdata/sampleinfo_mlst.json
microSALT-3.0.1.data/data/testdata/sampleinfo_samples.json
tests/__init__.py
tests/test_commands.py
tests/test_config.py
tests/test_database.py
tests/test_jobcreator.py
tests/test_scraper.py
tests/test_webserver.py
tests/testdata/ACC5551.json
tests/testdata/MIC3109.json
tests/testdata/MIC4107.json
tests/testdata/MIC4109.json
tests/testdata/alignment.stats.cov
tests/testdata/alignment.stats.dup
tests/testdata/alignment.stats.ins
tests/testdata/alignment.stats.map
tests/testdata/alignment.stats.raw
tests/testdata/alignment.stats.ref
microSALT-3.0.1.dist-info/LICENSE
microSALT-3.0.1.dist-info/METADATA
microSALT-3.0.1.dist-info/WHEEL
microSALT-3.0.1.dist-info/entry_points.txt
microSALT-3.0.1.dist-info/top_level.txt
microSALT-3.0.1.dist-info/RECORD
