Metadata-Version: 2.1
Name: microSALT
Version: 3.0.1
Summary: UNKNOWN
Home-page: https://github.com/Clinical-Genomics/microSALT
Author: Isak Sylvin
Author-email: isak.sylvin@scilifelab.se
License: UNKNOWN
Platform: UNKNOWN
Requires-Dist: biopython
Requires-Dist: bs4
Requires-Dist: click (==7.0)
Requires-Dist: flask
Requires-Dist: flask-sqlalchemy
Requires-Dist: pymysql
Requires-Dist: pyyaml
Requires-Dist: sqlalchemy
Requires-Dist: genologics
